[{"permalink":"//","layout":"default","title":"Übersicht Test Doku","content":"# Übersicht Test Doku\n\nblabla text Hier\n","dir":"/","name":"README.md","path":"README.md","url":"/"},{"layout":"default","title":"Test-Doku","content":"# Test-Doku\n\n1. [Generate with the same files and folders](https://github.com/rundocs/starter-slim/generate) from this repository\n2. Set up your GitHub Pages to source(`/`)\n3. Now you can view your documentation in your site\n","dir":"/","name":"test1.md","path":"test1.md","url":"/test1.html"}]